LICENSE
MANIFEST.in
README.md
pyproject.toml
setup.py
cuda/algorithms.cuh
cuda/high_level.cu
cuda/kernels.cuh
cuda/neuzip.cu
neuzip/__init__.py
neuzip/binding.py
neuzip/utils.py
neuzip.egg-info/PKG-INFO
neuzip.egg-info/SOURCES.txt
neuzip.egg-info/dependency_links.txt
neuzip.egg-info/requires.txt
neuzip.egg-info/top_level.txt
neuzip/nn/__init__.py
neuzip/nn/conv1d.py
neuzip/nn/embedding.py
neuzip/nn/linear.py
neuzip/nn/module.py
neuzip/ops/__init__.py
neuzip/ops/conv1d.py
neuzip/ops/linear.py